pywevolor/__init__.py
pywevolor/wevolor.py
pywevolor-0.0.2.dist-info/LICENSE
pywevolor-0.0.2.dist-info/METADATA
pywevolor-0.0.2.dist-info/WHEEL
pywevolor-0.0.2.dist-info/top_level.txt
pywevolor-0.0.2.dist-info/RECORD
