Metadata-Version: 2.1
Name: pywevolor
Version: 0.0.2
Summary: Python wrapper for interfaceing with the Wevolor API
Home-page: https://github.com/timstallmann/pywevolor
Author: Tim Stallmann
Author-email: tim@tim-maps.com
License: UNKNOWN
Project-URL: Bug Tracker, https://github.com/timstallmann/pywevolorissues
Platform: UNKNOWN
Classifier: Programming Language :: Python :: 3
Classifier: License :: OSI Approved :: MIT License
Classifier: Operating System :: OS Independent
Requires-Python: >=3.6
License-File: LICENSE
